Metadata-Version: 2.1
Name: MODULOS-TESTS
Version: 0.0.1
Summary: My short description
Author: MARCIO DIAS
Author-email: marcioalexdias@gmail.com
Requires-Python: >=3.8
